{
  "$schema": "https://schema.management.azure.com/schemas/2019-04-01/deploymentTemplate.json#",
  "contentVersion": "1.0.0.0",
  "metadata": {
    "_generator": {
      "name": "AzOps"
    }
  },
  "parameters": {},
  "variables": {},
  "resources": [
    {
      "type": "Microsoft.Authorization/roleAssignments",
      "name": "aa9b3a36-f9ff-4866-9caa-ec63596c4576",
      "apiVersion": "2022-01-01-preview",
      "properties": {
        "DisplayName": "Adele Vance",
        "ObjectType": "User",
        "PrincipalId": "e20c40b1-88b0-40f5-af82-5c74ee70e66d",
        "RoleDefinitionId": "/providers/Microsoft.Authorization/RoleDefinitions/8e3af657-a8ff-443c-a75c-2fe8c4bcb635",
        "RoleDefinitionName": "Owner"
      }
    }
  ],
  "outputs": {}
}
