{
  "$schema": "https://schema.management.azure.com/schemas/2019-04-01/deploymentTemplate.json#",
  "contentVersion": "1.0.0.0",
  "metadata": {
    "_generator": {
      "name": "AzOps"
    }
  },
  "parameters": {},
  "variables": {},
  "resources": [
    {
      "apiVersion": "2020-08-01",
      "name": "north-star-law/LogManagement(north-star-law)_LogManagement|ListAllIISLogEntries",
      "properties": {
        "category": "Log Management",
        "displayName": "All IIS Log Entries",
        "query": "search * | extend Type = $table | where Type == W3CIISLog | sort by TimeGenerated desc\r\n// Oql: Type=W3CIISLog // Args: {OQ: True; WorkspaceId: 00000000-0000-0000-0000-000000000000} // Settings: {PEF: True; SortI: True; SortF: True} // Version: 0.1.122",
        "version": 2
      },
      "type": "Microsoft.OperationalInsights/workspaces/savedSearches"
    }
  ],
  "outputs": {}
}
